psykit/__init__.py
psykit/__version__
psykit/gltools.py
psykit/offscreen.py
psykit/pupillabs.py
psykit/stereomode.py
psykit/vpixx.py
psykit/data/__init__.py
psykit/data/apriltags_tag36h11_0-23.jpg
psykit/data/apriltags_tag36h11_24-47.jpg
psykit/demos/__init__.py
psykit/demos/adjust_fixation.py
psykit/demos/draw_texture.py
psykit/demos/dualhead_mode.py
psykit/demos/jgscy.png
psykit/demos/minimum_adaptor.py
psykit/demos/minimum_example.py
psykit/demos/offscreen_window.py
psykit/demos/propixx_movie_compensated.py
psykit/demos/propixx_polarizer.py
psykit/demos/propixx_polarizer_simple.py
psykit/demos/qtywscy.jpg
psykit/demos/realtime_video_filtering.py
psykit/demos/stereo_modes.py
psykit/demos/visual_stims.py
psykit-1.2.8.dist-info/licenses/LICENSE.txt
psykit-1.2.8.dist-info/METADATA
psykit-1.2.8.dist-info/WHEEL
psykit-1.2.8.dist-info/top_level.txt
psykit-1.2.8.dist-info/RECORD
