Metadata-Version: 2.4
Name: psykit
Version: 1.2.8
Summary: A PsychoPy extension for stereoscopic display and more.
Home-page: https://github.com/herrlich10/psykit
Author: herrlich10
Author-email: herrlich10@gmail.com
Classifier: Programming Language :: Python :: 3
Classifier: License :: OSI Approved :: MIT License
Classifier: Operating System :: OS Independent
Requires-Python: >=3.6
License-File: LICENSE.txt
Dynamic: author
Dynamic: author-email
Dynamic: classifier
Dynamic: description
Dynamic: description-content-type
Dynamic: home-page
Dynamic: license-file
Dynamic: requires-python
Dynamic: summary
